<?xml version="1.0" encoding="UTF-8"?>
<!DOCTYPE pkgmetadata SYSTEM "http://www.gentoo.org/dtd/metadata.dtd">
<pkgmetadata>
  <longdescription>
    SVH Driver wrapper to enable control of the Schunk five finger hand
  </longdescription>
  <maintainer type="person">
    <email>hunter@openrobotics.org</email>
    <name>Hunter L. Allen</name>
  </maintainer>
  <upstream>
    <maintainer status="active">
      <email>heppner@fzi.de</email>
      <name>Georg Heppner</name>
    </maintainer>
    <bugs-to>https://github.com/fzi-forschungszentrum-informatik/schunk_svh_driver/issues</bugs-to>
  </upstream>
</pkgmetadata>
