<?xml version="1.0" encoding="UTF-8"?>
<!DOCTYPE pkgmetadata SYSTEM "http://www.gentoo.org/dtd/metadata.dtd">
<pkgmetadata>
  <longdescription>
    The goto_crossing package provides a goToGoal behavior
	  to a crossing center if the crossing has at least three
	  frontiers and some kind of move forward behavior if it
	  has two or less frontiers.
  </longdescription>
  <maintainer type="person">
    <email>hunter@openrobotics.org</email>
    <name>Hunter L. Allen</name>
  </maintainer>
  <upstream>
    <maintainer status="active">
      <email>gael.ecorchard@ciirc.cvut.cz</email>
      <name>Gaël Ecorchard</name>
    </maintainer>
    <bugs-to>https://github.com/lama-imr/lama_utilities/issues</bugs-to>
  </upstream>
</pkgmetadata>
