<?xml version="1.0" encoding="UTF-8"?>
<!DOCTYPE pkgmetadata SYSTEM "http://www.gentoo.org/dtd/metadata.dtd">
<pkgmetadata>
  <longdescription>
    <p>
      MoveIt plugins for the ABB 2400 (and variants).
    </p>
    <p>
      This package contains plugins for use with MoveIt and ABB 2400 manipulators.
      Plugins included support the 2400. See the ABB 2400 support package for
      information on used joint angle and velocity limits.
    </p>
    <p>
      Before using any of the plugins included in this package, be sure to
      check they are correct for the particular robot model and configuration
      you intend to use them with.
    </p>
  </longdescription>
  <maintainer type="person">
    <email>hunterlallen@protonmail.com</email>
    <name>Hunter L. Allen</name>
  </maintainer>
  <upstream>
    <maintainer status="active">
      <email>levi.armstrong@swri.org</email>
      <name>Levi Armstrong (Southwest Research Institute)</name>
    </maintainer>
    <bugs-to>https://github.com/ros-industrial/abb/issues</bugs-to>
  </upstream>
</pkgmetadata>
