<?xml version="1.0" encoding="UTF-8"?>
<!DOCTYPE pkgmetadata SYSTEM "http://www.gentoo.org/dtd/metadata.dtd">
<pkgmetadata>
  <longdescription>
    The gazebo_mimic package
  </longdescription>
  <maintainer type="person">
    <email>hunter@openrobotics.org</email>
    <name>Hunter L. Allen</name>
  </maintainer>
  <upstream>
    <maintainer status="active">
      <email>robert.krug@oru.se</email>
      <name>Robert Krug</name>
    </maintainer>
    <bugs-to>https://github.com/OrebroUniversity/yumi_release/issues</bugs-to>
  </upstream>
</pkgmetadata>
