<?xml version="1.0" encoding="UTF-8"?>
<!DOCTYPE pkgmetadata SYSTEM "http://www.gentoo.org/dtd/metadata.dtd">
<pkgmetadata>
  <longdescription>
    This package holds common configuration files for running the  <a href="http://ros.org/wiki/move_base">move_base</a> node and other navigation related nodes on the <a href="http://ros.org/wiki/care-o-bot">Care-O-bot</a>.
  </longdescription>
  <maintainer type="person">
    <email>hunter@openrobotics.org</email>
    <name>Hunter L. Allen</name>
  </maintainer>
  <upstream>
    <maintainer status="active">
      <email>fez@ipa.fraunhofer.de</email>
      <name>Felix Zeltner</name>
    </maintainer>
    <bugs-to>https://github.com/ipa320/cob_navigation/issues</bugs-to>
  </upstream>
</pkgmetadata>
